README.rst
fwmacro.py
setup.cfg
setup.py
fwmacro.egg-info/PKG-INFO
fwmacro.egg-info/SOURCES.txt
fwmacro.egg-info/dependency_links.txt
fwmacro.egg-info/entry_points.txt
fwmacro.egg-info/requires.txt
fwmacro.egg-info/top_level.txt