Metadata-Version: 1.1
Name: fwmacro
Version: 0.9.6
Summary: Firewall macro compiler
Home-page: https://github.com/keesbos/fwmacro
Author: Kees Bos
Author-email: k.bos@capitar.com
License: MIT
Keywords: Networking,Systems Administration,Firewall,iptables,ip6tables
Platform: UNKNOWN
Classifier: Development Status :: 4 - Beta
Classifier: Programming Language :: Python :: 2.6
Classifier: Programming Language :: Python :: 2.7
Classifier: Programming Language :: Python :: 3
Classifier: Environment :: Console
Classifier: Intended Audience :: Developers
Classifier: Intended Audience :: System Administrators
Classifier: License :: OSI Approved :: MIT License
Classifier: Natural Language :: English
Classifier: Operating System :: POSIX :: Linux
Classifier: Topic :: System :: Networking
Classifier: Topic :: System :: Networking :: Firewalls
Classifier: Topic :: System :: Operating System
Classifier: Topic :: System :: Systems Administration
Classifier: Topic :: Utilities
